combicode/__init__.py
combicode/main.py
combicode-1.7.4.dist-info/licenses/LICENSE
combicode-1.7.4.dist-info/METADATA
combicode-1.7.4.dist-info/WHEEL
combicode-1.7.4.dist-info/entry_points.txt
combicode-1.7.4.dist-info/top_level.txt
combicode-1.7.4.dist-info/RECORD
