Metadata-Version: 2.4
Name: combicode
Version: 1.7.4
Summary: A CLI tool to combine a project's codebase into a single file for LLM context.
Author: A. Aurelions
License: MIT License
Project-URL: Homepage, https://github.com/aaurelions/combicode
Project-URL: Bug Tracker, https://github.com/aaurelions/combicode/issues
Classifier: Programming Language :: Python :: 3
Classifier: License :: OSI Approved :: MIT License
Classifier: Operating System :: OS Independent
Classifier: Topic :: Utilities
Classifier: Environment :: Console
Requires-Python: >=3.8
License-File: LICENSE
Requires-Dist: click>=8.0
Requires-Dist: pathspec>=0.9
Provides-Extra: test
Requires-Dist: pytest; extra == "test"
Dynamic: license-file
